unet/__init__.py
unet/callbacks.py
unet/metrics.py
unet/schedulers.py
unet/trainer.py
unet/unet.py
unet/utils.py
unet/datasets/__init__.py
unet/datasets/circles.py
unet/datasets/oxford_iiit_pet.py
unet_jlbaker-0.0.1.dist-info/AUTHORS.rst
unet_jlbaker-0.0.1.dist-info/LICENSE.txt
unet_jlbaker-0.0.1.dist-info/METADATA
unet_jlbaker-0.0.1.dist-info/WHEEL
unet_jlbaker-0.0.1.dist-info/top_level.txt
unet_jlbaker-0.0.1.dist-info/RECORD
